[
  {
    "Driver":"ALB",
    "FP1_AvgLapTime":103.5395,
    "FP1_BestLapTime":89.606,
    "FP1_LapTimeStd":17.2279064925,
    "FP1_LapCount":14.0,
    "FP1_BestSector1Time":32.673,
    "FP1_AvgSector1Time":45.3721052632,
    "FP1_BestSector2Time":28.268,
    "FP1_AvgSector2Time":38.0833478261,
    "FP1_BestSector3Time":28.615,
    "FP1_AvgSector3Time":35.9593913043,
    "FP1_Laps_SOFT":6.0,
    "FP1_Laps_MEDIUM":17.0,
    "FP1_Laps_HARD":0.0,
    "FP1_Laps_INTERMEDIATE":0.0,
    "FP1_Laps_WET":0.0,
    "FP1_MaxTyreAge":17.0,
    "FP1_AvgTyreAge":7.5652173913,
    "FP1_MaxTrapSpeed":328.0,
    "FP1_AvgSpeed":244.2841249022,
    "FP1_AvgThrottle":80.2632796961,
    "FP1_FullThrottlePct":0.6937869822,
    "FP1_BrakingPct":0.1198224852,
    "FP1_DRSDeploymentPct":0.2485207101,
    "FP2_AvgLapTime":109.9677142857,
    "FP2_BestLapTime":89.22,
    "FP2_LapTimeStd":20.9482315884,
    "FP2_LapCount":14.0,
    "FP2_BestSector1Time":32.49,
    "FP2_AvgSector1Time":44.9253157895,
    "FP2_BestSector2Time":28.252,
    "FP2_AvgSector2Time":36.7570869565,
    "FP2_BestSector3Time":28.43,
    "FP2_AvgSector3Time":37.1882727273,
    "FP2_Laps_SOFT":7.0,
    "FP2_Laps_MEDIUM":0.0,
    "FP2_Laps_HARD":16.0,
    "FP2_Laps_INTERMEDIATE":0.0,
    "FP2_Laps_WET":0.0,
    "FP2_MaxTyreAge":16.0,
    "FP2_AvgTyreAge":7.1304347826,
    "FP2_MaxTrapSpeed":331.0,
    "FP2_AvgSpeed":246.0544387399,
    "FP2_AvgThrottle":80.0082698198,
    "FP2_FullThrottlePct":0.6609195402,
    "FP2_BrakingPct":0.1379310345,
    "FP2_DRSDeploymentPct":0.2485632184,
    "FP3_AvgLapTime":115.6682727273,
    "FP3_BestLapTime":88.389,
    "FP3_LapTimeStd":22.7573027712,
    "FP3_LapCount":11.0,
    "FP3_BestSector1Time":32.137,
    "FP3_AvgSector1Time":44.4922727273,
    "FP3_BestSector2Time":27.885,
    "FP3_AvgSector2Time":35.273875,
    "FP3_BestSector3Time":28.367,
    "FP3_AvgSector3Time":35.515125,
    "FP3_Laps_SOFT":16.0,
    "FP3_Laps_MEDIUM":0.0,
    "FP3_Laps_HARD":0.0,
    "FP3_Laps_INTERMEDIATE":0.0,
    "FP3_Laps_WET":0.0,
    "FP3_MaxTyreAge":9.0,
    "FP3_AvgTyreAge":4.5625,
    "FP3_MaxTrapSpeed":336.0,
    "FP3_AvgSpeed":249.8771046455,
    "FP3_AvgThrottle":80.5164677877,
    "FP3_FullThrottlePct":0.7082111437,
    "FP3_BrakingPct":0.1480938416,
    "FP3_DRSDeploymentPct":0.2478005865,
    "MaxTrapSpeed":336.0,
    "AvgTrapSpeed":331.6666666667,
    "FullThrottlePct":0.6876392221,
    "BrakingPct":0.1352824538,
    "DRSDeploymentPct":0.2482948383,
    "BrakePointDelta":-5.1739378655,
    "AvgAirTemp":29.0129783951,
    "AvgTrackTemp":44.2638528807,
    "AvgHumidity":58.9753600823,
    "AvgWindSpeed":1.4758899177,
    "AvgWindDirection":235.7989711934,
    "TrackTempDeltaFP1toFP3":1.7491820988
  },
  {
    "Driver":"ALO",
    "FP1_AvgLapTime":107.1387647059,
    "FP1_BestLapTime":89.976,
    "FP1_LapTimeStd":20.9497646244,
    "FP1_LapCount":17.0,
    "FP1_BestSector1Time":32.734,
    "FP1_AvgSector1Time":43.582047619,
    "FP1_BestSector2Time":28.307,
    "FP1_AvgSector2Time":36.9564166667,
    "FP1_BestSector3Time":28.854,
    "FP1_AvgSector3Time":36.1315,
    "FP1_Laps_SOFT":6.0,
    "FP1_Laps_MEDIUM":18.0,
    "FP1_Laps_HARD":0.0,
    "FP1_Laps_INTERMEDIATE":0.0,
    "FP1_Laps_WET":0.0,
    "FP1_MaxTyreAge":18.0,
    "FP1_AvgTyreAge":8.0,
    "FP1_MaxTrapSpeed":324.0,
    "FP1_AvgSpeed":243.1022776713,
    "FP1_AvgThrottle":80.1217955288,
    "FP1_FullThrottlePct":0.737388724,
    "FP1_BrakingPct":0.1142433234,
    "FP1_DRSDeploymentPct":0.2462908012,
    "FP2_AvgLapTime":111.4753,
    "FP2_BestLapTime":89.662,
    "FP2_LapTimeStd":21.3814118183,
    "FP2_LapCount":10.0,
    "FP2_BestSector1Time":32.621,
    "FP2_AvgSector1Time":46.5057142857,
    "FP2_BestSector2Time":28.316,
    "FP2_AvgSector2Time":39.0810555556,
    "FP2_BestSector3Time":28.687,
    "FP2_AvgSector3Time":38.6326470588,
    "FP2_Laps_SOFT":7.0,
    "FP2_Laps_MEDIUM":11.0,
    "FP2_Laps_HARD":0.0,
    "FP2_Laps_INTERMEDIATE":0.0,
    "FP2_Laps_WET":0.0,
    "FP2_MaxTyreAge":11.0,
    "FP2_AvgTyreAge":5.2222222222,
    "FP2_MaxTrapSpeed":329.0,
    "FP2_AvgSpeed":244.6316850413,
    "FP2_AvgThrottle":79.5992792257,
    "FP2_FullThrottlePct":0.723880597,
    "FP2_BrakingPct":0.1164179104,
    "FP2_DRSDeploymentPct":0.2597014925,
    "FP3_AvgLapTime":110.17775,
    "FP3_BestLapTime":88.888,
    "FP3_LapTimeStd":22.7412654846,
    "FP3_LapCount":12.0,
    "FP3_BestSector1Time":32.243,
    "FP3_AvgSector1Time":49.003,
    "FP3_BestSector2Time":28.012,
    "FP3_AvgSector2Time":35.9582105263,
    "FP3_BestSector3Time":28.633,
    "FP3_AvgSector3Time":38.7467894737,
    "FP3_Laps_SOFT":16.0,
    "FP3_Laps_MEDIUM":1.0,
    "FP3_Laps_HARD":2.0,
    "FP3_Laps_INTERMEDIATE":0.0,
    "FP3_Laps_WET":0.0,
    "FP3_MaxTyreAge":10.0,
    "FP3_AvgTyreAge":4.1578947368,
    "FP3_MaxTrapSpeed":330.0,
    "FP3_AvgSpeed":250.2024317245,
    "FP3_AvgThrottle":81.7887110096,
    "FP3_FullThrottlePct":0.7511111111,
    "FP3_BrakingPct":0.1022222222,
    "FP3_DRSDeploymentPct":0.2681481481,
    "MaxTrapSpeed":330.0,
    "AvgTrapSpeed":327.6666666667,
    "FullThrottlePct":0.7374601441,
    "BrakingPct":0.110961152,
    "DRSDeploymentPct":0.258046814,
    "BrakePointDelta":10.8157843567,
    "AvgAirTemp":29.0129783951,
    "AvgTrackTemp":44.2638528807,
    "AvgHumidity":58.9753600823,
    "AvgWindSpeed":1.4758899177,
    "AvgWindDirection":235.7989711934,
    "TrackTempDeltaFP1toFP3":1.7491820988
  },
  {
    "Driver":"ANT",
    "FP1_AvgLapTime":102.8245333333,
    "FP1_BestLapTime":89.934,
    "FP1_LapTimeStd":17.2862875915,
    "FP1_LapCount":15.0,
    "FP1_BestSector1Time":32.878,
    "FP1_AvgSector1Time":46.2766666667,
    "FP1_BestSector2Time":28.272,
    "FP1_AvgSector2Time":37.1727916667,
    "FP1_BestSector3Time":28.784,
    "FP1_AvgSector3Time":36.3530416667,
    "FP1_Laps_SOFT":6.0,
    "FP1_Laps_MEDIUM":18.0,
    "FP1_Laps_HARD":0.0,
    "FP1_Laps_INTERMEDIATE":0.0,
    "FP1_Laps_WET":0.0,
    "FP1_MaxTyreAge":18.0,
    "FP1_AvgTyreAge":7.875,
    "FP1_MaxTrapSpeed":327.0,
    "FP1_AvgSpeed":245.8698788662,
    "FP1_AvgThrottle":80.8186044075,
    "FP1_FullThrottlePct":0.6893491124,
    "FP1_BrakingPct":0.1272189349,
    "FP1_DRSDeploymentPct":0.2618343195,
    "FP2_AvgLapTime":99.11125,
    "FP2_BestLapTime":89.242,
    "FP2_LapTimeStd":17.0431626068,
    "FP2_LapCount":8.0,
    "FP2_BestSector1Time":32.594,
    "FP2_AvgSector1Time":48.601,
    "FP2_BestSector2Time":28.252,
    "FP2_AvgSector2Time":41.486875,
    "FP2_BestSector3Time":28.396,
    "FP2_AvgSector3Time":37.22025,
    "FP2_Laps_SOFT":6.0,
    "FP2_Laps_MEDIUM":10.0,
    "FP2_Laps_HARD":0.0,
    "FP2_Laps_INTERMEDIATE":0.0,
    "FP2_Laps_WET":0.0,
    "FP2_MaxTyreAge":10.0,
    "FP2_AvgTyreAge":4.75,
    "FP2_MaxTrapSpeed":330.0,
    "FP2_AvgSpeed":246.4263657236,
    "FP2_AvgThrottle":81.1692599547,
    "FP2_FullThrottlePct":0.6729106628,
    "FP2_BrakingPct":0.1152737752,
    "FP2_DRSDeploymentPct":0.257925072,
    "FP3_AvgLapTime":113.79275,
    "FP3_BestLapTime":88.679,
    "FP3_LapTimeStd":24.8792553386,
    "FP3_LapCount":12.0,
    "FP3_BestSector1Time":32.286,
    "FP3_AvgSector1Time":48.1974285714,
    "FP3_BestSector2Time":27.88,
    "FP3_AvgSector2Time":36.461,
    "FP3_BestSector3Time":28.423,
    "FP3_AvgSector3Time":36.1189444444,
    "FP3_Laps_SOFT":18.0,
    "FP3_Laps_MEDIUM":0.0,
    "FP3_Laps_HARD":0.0,
    "FP3_Laps_INTERMEDIATE":0.0,
    "FP3_Laps_WET":0.0,
    "FP3_MaxTyreAge":12.0,
    "FP3_AvgTyreAge":5.5,
    "FP3_MaxTrapSpeed":332.0,
    "FP3_AvgSpeed":249.3265568473,
    "FP3_AvgThrottle":81.2640268327,
    "FP3_FullThrottlePct":0.6959064327,
    "FP3_BrakingPct":0.1198830409,
    "FP3_DRSDeploymentPct":0.2485380117,
    "MaxTrapSpeed":332.0,
    "AvgTrapSpeed":329.6666666667,
    "FullThrottlePct":0.6860554027,
    "BrakingPct":0.120791917,
    "DRSDeploymentPct":0.2560991344,
    "BrakePointDelta":5.1618028752,
    "AvgAirTemp":29.0129783951,
    "AvgTrackTemp":44.2638528807,
    "AvgHumidity":58.9753600823,
    "AvgWindSpeed":1.4758899177,
    "AvgWindDirection":235.7989711934,
    "TrackTempDeltaFP1toFP3":1.7491820988
  },
  {
    "Driver":"BEA",
    "FP1_AvgLapTime":109.7244615385,
    "FP1_BestLapTime":90.595,
    "FP1_LapTimeStd":22.8024751603,
    "FP1_LapCount":13.0,
    "FP1_BestSector1Time":32.916,
    "FP1_AvgSector1Time":48.8045,
    "FP1_BestSector2Time":28.391,
    "FP1_AvgSector2Time":36.4104761905,
    "FP1_BestSector3Time":29.139,
    "FP1_AvgSector3Time":37.0586190476,
    "FP1_Laps_SOFT":15.0,
    "FP1_Laps_MEDIUM":0.0,
    "FP1_Laps_HARD":6.0,
    "FP1_Laps_INTERMEDIATE":0.0,
    "FP1_Laps_WET":0.0,
    "FP1_MaxTyreAge":15.0,
    "FP1_AvgTyreAge":6.7142857143,
    "FP1_MaxTrapSpeed":329.0,
    "FP1_AvgSpeed":246.1563269645,
    "FP1_AvgThrottle":82.3030925831,
    "FP1_FullThrottlePct":0.7299270073,
    "FP1_BrakingPct":0.1532846715,
    "FP1_DRSDeploymentPct":0.2613138686,
    "FP2_AvgLapTime":104.5008888889,
    "FP2_BestLapTime":89.754,
    "FP2_LapTimeStd":20.0201527432,
    "FP2_LapCount":9.0,
    "FP2_BestSector1Time":32.882,
    "FP2_AvgSector1Time":46.2889285714,
    "FP2_BestSector2Time":28.19,
    "FP2_AvgSector2Time":35.8530526316,
    "FP2_BestSector3Time":28.665,
    "FP2_AvgSector3Time":37.6297777778,
    "FP2_Laps_SOFT":6.0,
    "FP2_Laps_MEDIUM":13.0,
    "FP2_Laps_HARD":0.0,
    "FP2_Laps_INTERMEDIATE":0.0,
    "FP2_Laps_WET":0.0,
    "FP2_MaxTyreAge":13.0,
    "FP2_AvgTyreAge":5.8947368421,
    "FP2_MaxTrapSpeed":331.0,
    "FP2_AvgSpeed":246.5903313293,
    "FP2_AvgThrottle":80.3546837252,
    "FP2_FullThrottlePct":0.6800595238,
    "FP2_BrakingPct":0.1413690476,
    "FP2_DRSDeploymentPct":0.2693452381,
    "FP3_AvgLapTime":104.89175,
    "FP3_BestLapTime":88.989,
    "FP3_LapTimeStd":18.2372782568,
    "FP3_LapCount":8.0,
    "FP3_BestSector1Time":32.532,
    "FP3_AvgSector1Time":45.5699,
    "FP3_BestSector2Time":27.975,
    "FP3_AvgSector2Time":37.9625333333,
    "FP3_BestSector3Time":28.475,
    "FP3_AvgSector3Time":36.6707333333,
    "FP3_Laps_SOFT":15.0,
    "FP3_Laps_MEDIUM":0.0,
    "FP3_Laps_HARD":0.0,
    "FP3_Laps_INTERMEDIATE":0.0,
    "FP3_Laps_WET":0.0,
    "FP3_MaxTyreAge":9.0,
    "FP3_AvgTyreAge":4.4,
    "FP3_MaxTrapSpeed":331.0,
    "FP3_AvgSpeed":247.8451289664,
    "FP3_AvgThrottle":81.1690173061,
    "FP3_FullThrottlePct":0.6901615272,
    "FP3_BrakingPct":0.1160058737,
    "FP3_DRSDeploymentPct":0.2599118943,
    "MaxTrapSpeed":331.0,
    "AvgTrapSpeed":330.3333333333,
    "FullThrottlePct":0.7000493528,
    "BrakingPct":0.136886531,
    "DRSDeploymentPct":0.263523667,
    "BrakePointDelta":14.5806917641,
    "AvgAirTemp":29.0129783951,
    "AvgTrackTemp":44.2638528807,
    "AvgHumidity":58.9753600823,
    "AvgWindSpeed":1.4758899177,
    "AvgWindDirection":235.7989711934,
    "TrackTempDeltaFP1toFP3":1.7491820988
  },
  {
    "Driver":"BOR",
    "FP1_AvgLapTime":101.8784666667,
    "FP1_BestLapTime":91.038,
    "FP1_LapTimeStd":17.2559618346,
    "FP1_LapCount":15.0,
    "FP1_BestSector1Time":33.314,
    "FP1_AvgSector1Time":43.92215,
    "FP1_BestSector2Time":28.711,
    "FP1_AvgSector2Time":36.1383043478,
    "FP1_BestSector3Time":28.809,
    "FP1_AvgSector3Time":36.4824347826,
    "FP1_Laps_SOFT":6.0,
    "FP1_Laps_MEDIUM":17.0,
    "FP1_Laps_HARD":0.0,
    "FP1_Laps_INTERMEDIATE":0.0,
    "FP1_Laps_WET":0.0,
    "FP1_MaxTyreAge":17.0,
    "FP1_AvgTyreAge":7.5652173913,
    "FP1_MaxTrapSpeed":336.0,
    "FP1_AvgSpeed":241.4133010204,
    "FP1_AvgThrottle":76.2817361797,
    "FP1_FullThrottlePct":0.6277372263,
    "FP1_BrakingPct":0.1416058394,
    "FP1_DRSDeploymentPct":0.2306569343,
    "FP2_AvgLapTime":0.0,
    "FP2_BestLapTime":0.0,
    "FP2_LapTimeStd":0.0,
    "FP2_LapCount":0.0,
    "FP2_BestSector1Time":0.0,
    "FP2_AvgSector1Time":0.0,
    "FP2_BestSector2Time":0.0,
    "FP2_AvgSector2Time":0.0,
    "FP2_BestSector3Time":0.0,
    "FP2_AvgSector3Time":0.0,
    "FP2_Laps_SOFT":0.0,
    "FP2_Laps_MEDIUM":0.0,
    "FP2_Laps_HARD":0.0,
    "FP2_Laps_INTERMEDIATE":0.0,
    "FP2_Laps_WET":0.0,
    "FP2_MaxTyreAge":0.0,
    "FP2_AvgTyreAge":0.0,
    "FP2_MaxTrapSpeed":0.0,
    "FP2_AvgSpeed":0.0,
    "FP2_AvgThrottle":0.0,
    "FP2_FullThrottlePct":0.0,
    "FP2_BrakingPct":0.0,
    "FP2_DRSDeploymentPct":0.0,
    "FP3_AvgLapTime":101.39075,
    "FP3_BestLapTime":89.41,
    "FP3_LapTimeStd":17.5210433042,
    "FP3_LapCount":16.0,
    "FP3_BestSector1Time":32.665,
    "FP3_AvgSector1Time":43.3421904762,
    "FP3_BestSector2Time":28.238,
    "FP3_AvgSector2Time":36.0484166667,
    "FP3_BestSector3Time":28.507,
    "FP3_AvgSector3Time":37.0572916667,
    "FP3_Laps_SOFT":8.0,
    "FP3_Laps_MEDIUM":16.0,
    "FP3_Laps_HARD":0.0,
    "FP3_Laps_INTERMEDIATE":0.0,
    "FP3_Laps_WET":0.0,
    "FP3_MaxTyreAge":16.0,
    "FP3_AvgTyreAge":7.1666666667,
    "FP3_MaxTrapSpeed":338.0,
    "FP3_AvgSpeed":245.2573719043,
    "FP3_AvgThrottle":78.1649681319,
    "FP3_FullThrottlePct":0.6603498542,
    "FP3_BrakingPct":0.1341107872,
    "FP3_DRSDeploymentPct":0.2405247813,
    "MaxTrapSpeed":338.0,
    "AvgTrapSpeed":337.0,
    "FullThrottlePct":0.6440435403,
    "BrakingPct":0.1378583133,
    "DRSDeploymentPct":0.2355908578,
    "BrakePointDelta":-102.0040694444,
    "AvgAirTemp":29.0129783951,
    "AvgTrackTemp":44.2638528807,
    "AvgHumidity":58.9753600823,
    "AvgWindSpeed":1.4758899177,
    "AvgWindDirection":235.7989711934,
    "TrackTempDeltaFP1toFP3":1.7491820988
  },
  {
    "Driver":"DOO",
    "FP1_AvgLapTime":108.29375,
    "FP1_BestLapTime":90.183,
    "FP1_LapTimeStd":21.8885738031,
    "FP1_LapCount":16.0,
    "FP1_BestSector1Time":32.75,
    "FP1_AvgSector1Time":47.4069545455,
    "FP1_BestSector2Time":28.453,
    "FP1_AvgSector2Time":37.07256,
    "FP1_BestSector3Time":28.883,
    "FP1_AvgSector3Time":36.35004,
    "FP1_Laps_SOFT":6.0,
    "FP1_Laps_MEDIUM":19.0,
    "FP1_Laps_HARD":0.0,
    "FP1_Laps_INTERMEDIATE":0.0,
    "FP1_Laps_WET":0.0,
    "FP1_MaxTyreAge":19.0,
    "FP1_AvgTyreAge":8.44,
    "FP1_MaxTrapSpeed":331.0,
    "FP1_AvgSpeed":245.2636966264,
    "FP1_AvgThrottle":80.5880933394,
    "FP1_FullThrottlePct":0.6967455621,
    "FP1_BrakingPct":0.1331360947,
    "FP1_DRSDeploymentPct":0.2440828402,
    "FP2_AvgLapTime":111.0085384615,
    "FP2_BestLapTime":89.912,
    "FP2_LapTimeStd":22.0419558328,
    "FP2_LapCount":13.0,
    "FP2_BestSector1Time":32.917,
    "FP2_AvgSector1Time":44.9465,
    "FP2_BestSector2Time":28.291,
    "FP2_AvgSector2Time":36.2864,
    "FP2_BestSector3Time":28.704,
    "FP2_AvgSector3Time":36.41155,
    "FP2_Laps_SOFT":5.0,
    "FP2_Laps_MEDIUM":16.0,
    "FP2_Laps_HARD":0.0,
    "FP2_Laps_INTERMEDIATE":0.0,
    "FP2_Laps_WET":0.0,
    "FP2_MaxTyreAge":16.0,
    "FP2_AvgTyreAge":7.1904761905,
    "FP2_MaxTrapSpeed":334.0,
    "FP2_AvgSpeed":243.5310356216,
    "FP2_AvgThrottle":78.8550382415,
    "FP2_FullThrottlePct":0.6611940299,
    "FP2_BrakingPct":0.1298507463,
    "FP2_DRSDeploymentPct":0.2313432836,
    "FP3_AvgLapTime":111.8594166667,
    "FP3_BestLapTime":88.898,
    "FP3_LapTimeStd":24.9562171538,
    "FP3_LapCount":12.0,
    "FP3_BestSector1Time":32.435,
    "FP3_AvgSector1Time":50.5692941176,
    "FP3_BestSector2Time":28.062,
    "FP3_AvgSector2Time":37.9230952381,
    "FP3_BestSector3Time":28.388,
    "FP3_AvgSector3Time":37.1053333333,
    "FP3_Laps_SOFT":21.0,
    "FP3_Laps_MEDIUM":0.0,
    "FP3_Laps_HARD":0.0,
    "FP3_Laps_INTERMEDIATE":0.0,
    "FP3_Laps_WET":0.0,
    "FP3_MaxTyreAge":13.0,
    "FP3_AvgTyreAge":6.0476190476,
    "FP3_MaxTrapSpeed":335.0,
    "FP3_AvgSpeed":250.3340587503,
    "FP3_AvgThrottle":80.0117959991,
    "FP3_FullThrottlePct":0.6745213549,
    "FP3_BrakingPct":0.1487481591,
    "FP3_DRSDeploymentPct":0.2680412371,
    "MaxTrapSpeed":335.0,
    "AvgTrapSpeed":333.3333333333,
    "FullThrottlePct":0.6774869823,
    "BrakingPct":0.137245,
    "DRSDeploymentPct":0.2478224536,
    "BrakePointDelta":-8.2134749025,
    "AvgAirTemp":29.0129783951,
    "AvgTrackTemp":44.2638528807,
    "AvgHumidity":58.9753600823,
    "AvgWindSpeed":1.4758899177,
    "AvgWindDirection":235.7989711934,
    "TrackTempDeltaFP1toFP3":1.7491820988
  },
  {
    "Driver":"GAS",
    "FP1_AvgLapTime":104.1093125,
    "FP1_BestLapTime":89.239,
    "FP1_LapTimeStd":20.7137877583,
    "FP1_LapCount":16.0,
    "FP1_BestSector1Time":32.407,
    "FP1_AvgSector1Time":46.6885454545,
    "FP1_BestSector2Time":28.29,
    "FP1_AvgSector2Time":36.22688,
    "FP1_BestSector3Time":28.536,
    "FP1_AvgSector3Time":36.09244,
    "FP1_Laps_SOFT":5.0,
    "FP1_Laps_MEDIUM":20.0,
    "FP1_Laps_HARD":0.0,
    "FP1_Laps_INTERMEDIATE":0.0,
    "FP1_Laps_WET":0.0,
    "FP1_MaxTyreAge":20.0,
    "FP1_AvgTyreAge":9.0,
    "FP1_MaxTrapSpeed":332.0,
    "FP1_AvgSpeed":247.7928326115,
    "FP1_AvgThrottle":80.778549039,
    "FP1_FullThrottlePct":0.6919575114,
    "FP1_BrakingPct":0.1107738998,
    "FP1_DRSDeploymentPct":0.253414264,
    "FP2_AvgLapTime":109.3639333333,
    "FP2_BestLapTime":89.106,
    "FP2_LapTimeStd":18.9405663231,
    "FP2_LapCount":15.0,
    "FP2_BestSector1Time":32.528,
    "FP2_AvgSector1Time":43.0337777778,
    "FP2_BestSector2Time":28.177,
    "FP2_AvgSector2Time":35.8617272727,
    "FP2_BestSector3Time":28.401,
    "FP2_AvgSector3Time":34.6175714286,
    "FP2_Laps_SOFT":6.0,
    "FP2_Laps_MEDIUM":16.0,
    "FP2_Laps_HARD":0.0,
    "FP2_Laps_INTERMEDIATE":0.0,
    "FP2_Laps_WET":0.0,
    "FP2_MaxTyreAge":16.0,
    "FP2_AvgTyreAge":7.1363636364,
    "FP2_MaxTrapSpeed":332.0,
    "FP2_AvgSpeed":247.0503829276,
    "FP2_AvgThrottle":79.7081604066,
    "FP2_FullThrottlePct":0.6901615272,
    "FP2_BrakingPct":0.1204111601,
    "FP2_DRSDeploymentPct":0.2452276065,
    "FP3_AvgLapTime":106.236625,
    "FP3_BestLapTime":88.625,
    "FP3_LapTimeStd":24.4174488894,
    "FP3_LapCount":8.0,
    "FP3_BestSector1Time":32.198,
    "FP3_AvgSector1Time":51.6215,
    "FP3_BestSector2Time":28.062,
    "FP3_AvgSector2Time":38.3906875,
    "FP3_BestSector3Time":28.365,
    "FP3_AvgSector3Time":38.4040625,
    "FP3_Laps_SOFT":16.0,
    "FP3_Laps_MEDIUM":0.0,
    "FP3_Laps_HARD":0.0,
    "FP3_Laps_INTERMEDIATE":0.0,
    "FP3_Laps_WET":0.0,
    "FP3_MaxTyreAge":9.0,
    "FP3_AvgTyreAge":4.5625,
    "FP3_MaxTrapSpeed":334.0,
    "FP3_AvgSpeed":247.905259366,
    "FP3_AvgThrottle":80.1171505093,
    "FP3_FullThrottlePct":0.7026627219,
    "FP3_BrakingPct":0.1153846154,
    "FP3_DRSDeploymentPct":0.2366863905,
    "MaxTrapSpeed":334.0,
    "AvgTrapSpeed":332.6666666667,
    "FullThrottlePct":0.6949272535,
    "BrakingPct":0.1155232251,
    "DRSDeploymentPct":0.2451094203,
    "BrakePointDelta":4.7448584308,
    "AvgAirTemp":29.0129783951,
    "AvgTrackTemp":44.2638528807,
    "AvgHumidity":58.9753600823,
    "AvgWindSpeed":1.4758899177,
    "AvgWindDirection":235.7989711934,
    "TrackTempDeltaFP1toFP3":1.7491820988
  },
  {
    "Driver":"HAD",
    "FP1_AvgLapTime":115.4836666667,
    "FP1_BestLapTime":90.011,
    "FP1_LapTimeStd":25.1338053476,
    "FP1_LapCount":9.0,
    "FP1_BestSector1Time":32.847,
    "FP1_AvgSector1Time":48.9205384615,
    "FP1_BestSector2Time":28.32,
    "FP1_AvgSector2Time":39.2796666667,
    "FP1_BestSector3Time":28.844,
    "FP1_AvgSector3Time":40.7503333333,
    "FP1_Laps_SOFT":7.0,
    "FP1_Laps_MEDIUM":8.0,
    "FP1_Laps_HARD":0.0,
    "FP1_Laps_INTERMEDIATE":0.0,
    "FP1_Laps_WET":0.0,
    "FP1_MaxTyreAge":8.0,
    "FP1_AvgTyreAge":4.2666666667,
    "FP1_MaxTrapSpeed":332.0,
    "FP1_AvgSpeed":244.0756486557,
    "FP1_AvgThrottle":80.0918870062,
    "FP1_FullThrottlePct":0.6991404011,
    "FP1_BrakingPct":0.1146131805,
    "FP1_DRSDeploymentPct":0.2464183381,
    "FP2_AvgLapTime":109.3013,
    "FP2_BestLapTime":89.306,
    "FP2_LapTimeStd":20.8462221307,
    "FP2_LapCount":10.0,
    "FP2_BestSector1Time":32.584,
    "FP2_AvgSector1Time":46.1756153846,
    "FP2_BestSector2Time":28.221,
    "FP2_AvgSector2Time":35.0660588235,
    "FP2_BestSector3Time":28.473,
    "FP2_AvgSector3Time":34.4509375,
    "FP2_Laps_SOFT":7.0,
    "FP2_Laps_MEDIUM":10.0,
    "FP2_Laps_HARD":0.0,
    "FP2_Laps_INTERMEDIATE":0.0,
    "FP2_Laps_WET":0.0,
    "FP2_MaxTyreAge":10.0,
    "FP2_AvgTyreAge":4.1764705882,
    "FP2_MaxTrapSpeed":331.0,
    "FP2_AvgSpeed":245.3825959478,
    "FP2_AvgThrottle":78.8473868938,
    "FP2_FullThrottlePct":0.682962963,
    "FP2_BrakingPct":0.1259259259,
    "FP2_DRSDeploymentPct":0.2385185185,
    "FP3_AvgLapTime":112.9342727273,
    "FP3_BestLapTime":88.769,
    "FP3_LapTimeStd":23.6751390412,
    "FP3_LapCount":11.0,
    "FP3_BestSector1Time":32.359,
    "FP3_AvgSector1Time":43.9081666667,
    "FP3_BestSector2Time":28.012,
    "FP3_AvgSector2Time":35.8358823529,
    "FP3_BestSector3Time":28.398,
    "FP3_AvgSector3Time":39.1521176471,
    "FP3_Laps_SOFT":16.0,
    "FP3_Laps_MEDIUM":0.0,
    "FP3_Laps_HARD":1.0,
    "FP3_Laps_INTERMEDIATE":0.0,
    "FP3_Laps_WET":0.0,
    "FP3_MaxTyreAge":19.0,
    "FP3_AvgTyreAge":10.8823529412,
    "FP3_MaxTrapSpeed":333.0,
    "FP3_AvgSpeed":248.0395107375,
    "FP3_AvgThrottle":80.9973825377,
    "FP3_FullThrottlePct":0.7186588921,
    "FP3_BrakingPct":0.1195335277,
    "FP3_DRSDeploymentPct":0.2448979592,
    "MaxTrapSpeed":333.0,
    "AvgTrapSpeed":332.0,
    "FullThrottlePct":0.7002540854,
    "BrakingPct":0.1200242114,
    "DRSDeploymentPct":0.2432782719,
    "BrakePointDelta":4.2606917641,
    "AvgAirTemp":29.0129783951,
    "AvgTrackTemp":44.2638528807,
    "AvgHumidity":58.9753600823,
    "AvgWindSpeed":1.4758899177,
    "AvgWindDirection":235.7989711934,
    "TrackTempDeltaFP1toFP3":1.7491820988
  },
  {
    "Driver":"HAM",
    "FP1_AvgLapTime":103.6331111111,
    "FP1_BestLapTime":89.815,
    "FP1_LapTimeStd":20.5187576791,
    "FP1_LapCount":18.0,
    "FP1_BestSector1Time":32.699,
    "FP1_AvgSector1Time":48.8422916667,
    "FP1_BestSector2Time":28.288,
    "FP1_AvgSector2Time":38.1521481481,
    "FP1_BestSector3Time":28.793,
    "FP1_AvgSector3Time":35.4147407407,
    "FP1_Laps_SOFT":9.0,
    "FP1_Laps_MEDIUM":18.0,
    "FP1_Laps_HARD":0.0,
    "FP1_Laps_INTERMEDIATE":0.0,
    "FP1_Laps_WET":0.0,
    "FP1_MaxTyreAge":18.0,
    "FP1_AvgTyreAge":8.0,
    "FP1_MaxTrapSpeed":331.0,
    "FP1_AvgSpeed":245.3362931515,
    "FP1_AvgThrottle":82.4845022015,
    "FP1_FullThrottlePct":0.604197901,
    "FP1_BrakingPct":0.1274362819,
    "FP1_DRSDeploymentPct":0.2443778111,
    "FP2_AvgLapTime":110.7185333333,
    "FP2_BestLapTime":89.371,
    "FP2_LapTimeStd":19.9124309482,
    "FP2_LapCount":15.0,
    "FP2_BestSector1Time":32.623,
    "FP2_AvgSector1Time":48.6754444444,
    "FP2_BestSector2Time":28.175,
    "FP2_AvgSector2Time":37.5526363636,
    "FP2_BestSector3Time":28.537,
    "FP2_AvgSector3Time":34.9345454545,
    "FP2_Laps_SOFT":7.0,
    "FP2_Laps_MEDIUM":16.0,
    "FP2_Laps_HARD":0.0,
    "FP2_Laps_INTERMEDIATE":0.0,
    "FP2_Laps_WET":0.0,
    "FP2_MaxTyreAge":16.0,
    "FP2_AvgTyreAge":7.1304347826,
    "FP2_MaxTrapSpeed":332.0,
    "FP2_AvgSpeed":247.9095027404,
    "FP2_AvgThrottle":82.3035923129,
    "FP2_FullThrottlePct":0.5307017544,
    "FP2_BrakingPct":0.1271929825,
    "FP2_DRSDeploymentPct":0.2514619883,
    "FP3_AvgLapTime":107.8683,
    "FP3_BestLapTime":88.78,
    "FP3_LapTimeStd":21.964424853,
    "FP3_LapCount":10.0,
    "FP3_BestSector1Time":32.323,
    "FP3_AvgSector1Time":53.4280625,
    "FP3_BestSector2Time":27.979,
    "FP3_AvgSector2Time":45.52565,
    "FP3_BestSector3Time":28.451,
    "FP3_AvgSector3Time":38.41775,
    "FP3_Laps_SOFT":20.0,
    "FP3_Laps_MEDIUM":0.0,
    "FP3_Laps_HARD":0.0,
    "FP3_Laps_INTERMEDIATE":0.0,
    "FP3_Laps_WET":0.0,
    "FP3_MaxTyreAge":10.0,
    "FP3_AvgTyreAge":5.5,
    "FP3_MaxTrapSpeed":335.0,
    "FP3_AvgSpeed":247.5479870521,
    "FP3_AvgThrottle":80.7717388235,
    "FP3_FullThrottlePct":0.5267857143,
    "FP3_BrakingPct":0.1413690476,
    "FP3_DRSDeploymentPct":0.2485119048,
    "MaxTrapSpeed":335.0,
    "AvgTrapSpeed":332.6666666667,
    "FullThrottlePct":0.5538951232,
    "BrakingPct":0.1319994373,
    "DRSDeploymentPct":0.2481172347,
    "BrakePointDelta":7.1669880604,
    "AvgAirTemp":29.0129783951,
    "AvgTrackTemp":44.2638528807,
    "AvgHumidity":58.9753600823,
    "AvgWindSpeed":1.4758899177,
    "AvgWindDirection":235.7989711934,
    "TrackTempDeltaFP1toFP3":1.7491820988
  },
  {
    "Driver":"HUL",
    "FP1_AvgLapTime":105.3767222222,
    "FP1_BestLapTime":89.916,
    "FP1_LapTimeStd":19.9738975896,
    "FP1_LapCount":18.0,
    "FP1_BestSector1Time":32.738,
    "FP1_AvgSector1Time":45.1791818182,
    "FP1_BestSector2Time":28.26,
    "FP1_AvgSector2Time":33.9002,
    "FP1_BestSector3Time":28.805,
    "FP1_AvgSector3Time":35.74132,
    "FP1_Laps_SOFT":12.0,
    "FP1_Laps_MEDIUM":13.0,
    "FP1_Laps_HARD":0.0,
    "FP1_Laps_INTERMEDIATE":0.0,
    "FP1_Laps_WET":0.0,
    "FP1_MaxTyreAge":13.0,
    "FP1_AvgTyreAge":6.76,
    "FP1_MaxTrapSpeed":341.0,
    "FP1_AvgSpeed":244.8463127112,
    "FP1_AvgThrottle":79.170077999,
    "FP1_FullThrottlePct":0.6555232558,
    "FP1_BrakingPct":0.1453488372,
    "FP1_DRSDeploymentPct":0.2281976744,
    "FP2_AvgLapTime":102.8040833333,
    "FP2_BestLapTime":89.193,
    "FP2_LapTimeStd":15.8306733014,
    "FP2_LapCount":12.0,
    "FP2_BestSector1Time":32.691,
    "FP2_AvgSector1Time":42.5692941176,
    "FP2_BestSector2Time":28.11,
    "FP2_AvgSector2Time":36.63905,
    "FP2_BestSector3Time":28.392,
    "FP2_AvgSector3Time":35.8971,
    "FP2_Laps_SOFT":9.0,
    "FP2_Laps_MEDIUM":12.0,
    "FP2_Laps_HARD":0.0,
    "FP2_Laps_INTERMEDIATE":0.0,
    "FP2_Laps_WET":0.0,
    "FP2_MaxTyreAge":12.0,
    "FP2_AvgTyreAge":5.8571428571,
    "FP2_MaxTrapSpeed":337.0,
    "FP2_AvgSpeed":246.8058900154,
    "FP2_AvgThrottle":79.0491428892,
    "FP2_FullThrottlePct":0.6541916168,
    "FP2_BrakingPct":0.1437125749,
    "FP2_DRSDeploymentPct":0.247005988,
    "FP3_AvgLapTime":113.3258,
    "FP3_BestLapTime":89.22,
    "FP3_LapTimeStd":22.7129262061,
    "FP3_LapCount":10.0,
    "FP3_BestSector1Time":32.562,
    "FP3_AvgSector1Time":50.0231538462,
    "FP3_BestSector2Time":28.143,
    "FP3_AvgSector2Time":37.0019375,
    "FP3_BestSector3Time":28.486,
    "FP3_AvgSector3Time":37.773875,
    "FP3_Laps_SOFT":16.0,
    "FP3_Laps_MEDIUM":0.0,
    "FP3_Laps_HARD":0.0,
    "FP3_Laps_INTERMEDIATE":0.0,
    "FP3_Laps_WET":0.0,
    "FP3_MaxTyreAge":10.0,
    "FP3_AvgTyreAge":4.75,
    "FP3_MaxTrapSpeed":338.0,
    "FP3_AvgSpeed":246.6006979229,
    "FP3_AvgThrottle":80.0154547609,
    "FP3_FullThrottlePct":0.6863309353,
    "FP3_BrakingPct":0.1625899281,
    "FP3_DRSDeploymentPct":0.2575539568,
    "MaxTrapSpeed":341.0,
    "AvgTrapSpeed":338.6666666667,
    "FullThrottlePct":0.6653486026,
    "BrakingPct":0.1505504467,
    "DRSDeploymentPct":0.2442525398,
    "BrakePointDelta":8.6747658382,
    "AvgAirTemp":29.0129783951,
    "AvgTrackTemp":44.2638528807,
    "AvgHumidity":58.9753600823,
    "AvgWindSpeed":1.4758899177,
    "AvgWindDirection":235.7989711934,
    "TrackTempDeltaFP1toFP3":1.7491820988
  },
  {
    "Driver":"LAW",
    "FP1_AvgLapTime":106.7222727273,
    "FP1_BestLapTime":89.907,
    "FP1_LapTimeStd":19.3189771111,
    "FP1_LapCount":11.0,
    "FP1_BestSector1Time":32.89,
    "FP1_AvgSector1Time":46.453,
    "FP1_BestSector2Time":28.451,
    "FP1_AvgSector2Time":39.1253157895,
    "FP1_BestSector3Time":28.566,
    "FP1_AvgSector3Time":38.2734210526,
    "FP1_Laps_SOFT":8.0,
    "FP1_Laps_MEDIUM":11.0,
    "FP1_Laps_HARD":0.0,
    "FP1_Laps_INTERMEDIATE":0.0,
    "FP1_Laps_WET":0.0,
    "FP1_MaxTyreAge":11.0,
    "FP1_AvgTyreAge":5.3684210526,
    "FP1_MaxTrapSpeed":330.0,
    "FP1_AvgSpeed":243.989087827,
    "FP1_AvgThrottle":79.9706793664,
    "FP1_FullThrottlePct":0.697466468,
    "FP1_BrakingPct":0.1132637854,
    "FP1_DRSDeploymentPct":0.2384500745,
    "FP2_AvgLapTime":106.443,
    "FP2_BestLapTime":89.488,
    "FP2_LapTimeStd":17.2665145151,
    "FP2_LapCount":13.0,
    "FP2_BestSector1Time":32.662,
    "FP2_AvgSector1Time":41.3195333333,
    "FP2_BestSector2Time":28.255,
    "FP2_AvgSector2Time":34.9114761905,
    "FP2_BestSector3Time":28.443,
    "FP2_AvgSector3Time":35.9254285714,
    "FP2_Laps_SOFT":10.0,
    "FP2_Laps_MEDIUM":12.0,
    "FP2_Laps_HARD":0.0,
    "FP2_Laps_INTERMEDIATE":0.0,
    "FP2_Laps_WET":0.0,
    "FP2_MaxTyreAge":12.0,
    "FP2_AvgTyreAge":4.9545454545,
    "FP2_MaxTrapSpeed":328.0,
    "FP2_AvgSpeed":246.4134701232,
    "FP2_AvgThrottle":80.3102989626,
    "FP2_FullThrottlePct":0.6856287425,
    "FP2_BrakingPct":0.1077844311,
    "FP2_DRSDeploymentPct":0.2335329341,
    "FP3_AvgLapTime":120.2815,
    "FP3_BestLapTime":88.861,
    "FP3_LapTimeStd":22.7685912188,
    "FP3_LapCount":12.0,
    "FP3_BestSector1Time":32.347,
    "FP3_AvgSector1Time":49.6849230769,
    "FP3_BestSector2Time":28.053,
    "FP3_AvgSector2Time":35.5680555556,
    "FP3_BestSector3Time":28.406,
    "FP3_AvgSector3Time":39.1124444444,
    "FP3_Laps_SOFT":17.0,
    "FP3_Laps_MEDIUM":0.0,
    "FP3_Laps_HARD":1.0,
    "FP3_Laps_INTERMEDIATE":0.0,
    "FP3_Laps_WET":0.0,
    "FP3_MaxTyreAge":12.0,
    "FP3_AvgTyreAge":6.3333333333,
    "FP3_MaxTrapSpeed":331.0,
    "FP3_AvgSpeed":246.6022595338,
    "FP3_AvgThrottle":79.6508522252,
    "FP3_FullThrottlePct":0.688253012,
    "FP3_BrakingPct":0.1129518072,
    "FP3_DRSDeploymentPct":0.2454819277,
    "MaxTrapSpeed":331.0,
    "AvgTrapSpeed":329.6666666667,
    "FullThrottlePct":0.6904494075,
    "BrakingPct":0.1113333413,
    "DRSDeploymentPct":0.2391549788,
    "BrakePointDelta":2.2640250975,
    "AvgAirTemp":29.0129783951,
    "AvgTrackTemp":44.2638528807,
    "AvgHumidity":58.9753600823,
    "AvgWindSpeed":1.4758899177,
    "AvgWindDirection":235.7989711934,
    "TrackTempDeltaFP1toFP3":1.7491820988
  },
  {
    "Driver":"LEC",
    "FP1_AvgLapTime":99.7946315789,
    "FP1_BestLapTime":89.309,
    "FP1_LapTimeStd":13.4535904345,
    "FP1_LapCount":19.0,
    "FP1_BestSector1Time":32.488,
    "FP1_AvgSector1Time":44.35388,
    "FP1_BestSector2Time":28.154,
    "FP1_AvgSector2Time":37.0638214286,
    "FP1_BestSector3Time":28.667,
    "FP1_AvgSector3Time":34.6194285714,
    "FP1_Laps_SOFT":6.0,
    "FP1_Laps_MEDIUM":22.0,
    "FP1_Laps_HARD":0.0,
    "FP1_Laps_INTERMEDIATE":0.0,
    "FP1_Laps_WET":0.0,
    "FP1_MaxTyreAge":22.0,
    "FP1_AvgTyreAge":9.7857142857,
    "FP1_MaxTrapSpeed":330.0,
    "FP1_AvgSpeed":246.6470135741,
    "FP1_AvgThrottle":82.2070540826,
    "FP1_FullThrottlePct":0.7227866473,
    "FP1_BrakingPct":0.1175616836,
    "FP1_DRSDeploymentPct":0.2583454282,
    "FP2_AvgLapTime":113.5878571429,
    "FP2_BestLapTime":88.749,
    "FP2_LapTimeStd":21.5274391877,
    "FP2_LapCount":14.0,
    "FP2_BestSector1Time":32.436,
    "FP2_AvgSector1Time":43.0077058824,
    "FP2_BestSector2Time":28.062,
    "FP2_AvgSector2Time":39.0547619048,
    "FP2_BestSector3Time":28.251,
    "FP2_AvgSector3Time":38.0718571429,
    "FP2_Laps_SOFT":7.0,
    "FP2_Laps_MEDIUM":15.0,
    "FP2_Laps_HARD":0.0,
    "FP2_Laps_INTERMEDIATE":0.0,
    "FP2_Laps_WET":0.0,
    "FP2_MaxTyreAge":15.0,
    "FP2_AvgTyreAge":6.7272727273,
    "FP2_MaxTrapSpeed":331.0,
    "FP2_AvgSpeed":247.2662564615,
    "FP2_AvgThrottle":80.8574497604,
    "FP2_FullThrottlePct":0.6951951952,
    "FP2_BrakingPct":0.1366366366,
    "FP2_DRSDeploymentPct":0.2642642643,
    "FP3_AvgLapTime":102.4098181818,
    "FP3_BestLapTime":88.372,
    "FP3_LapTimeStd":19.5229455197,
    "FP3_LapCount":11.0,
    "FP3_BestSector1Time":32.151,
    "FP3_AvgSector1Time":48.1274117647,
    "FP3_BestSector2Time":27.982,
    "FP3_AvgSector2Time":42.0393333333,
    "FP3_BestSector3Time":28.239,
    "FP3_AvgSector3Time":38.6154285714,
    "FP3_Laps_SOFT":21.0,
    "FP3_Laps_MEDIUM":0.0,
    "FP3_Laps_HARD":0.0,
    "FP3_Laps_INTERMEDIATE":0.0,
    "FP3_Laps_WET":0.0,
    "FP3_MaxTyreAge":11.0,
    "FP3_AvgTyreAge":5.7619047619,
    "FP3_MaxTrapSpeed":336.0,
    "FP3_AvgSpeed":249.7630296374,
    "FP3_AvgThrottle":81.4856526119,
    "FP3_FullThrottlePct":0.7138728324,
    "FP3_BrakingPct":0.1401734104,
    "FP3_DRSDeploymentPct":0.2615606936,
    "MaxTrapSpeed":336.0,
    "AvgTrapSpeed":332.3333333333,
    "FullThrottlePct":0.710618225,
    "BrakingPct":0.1314572435,
    "DRSDeploymentPct":0.2613901287,
    "BrakePointDelta":5.2273584308,
    "AvgAirTemp":29.0129783951,
    "AvgTrackTemp":44.2638528807,
    "AvgHumidity":58.9753600823,
    "AvgWindSpeed":1.4758899177,
    "AvgWindDirection":235.7989711934,
    "TrackTempDeltaFP1toFP3":1.7491820988
  },
  {
    "Driver":"NOR",
    "FP1_AvgLapTime":107.2905714286,
    "FP1_BestLapTime":89.246,
    "FP1_LapTimeStd":22.1971816445,
    "FP1_LapCount":21.0,
    "FP1_BestSector1Time":32.322,
    "FP1_AvgSector1Time":41.7590454545,
    "FP1_BestSector2Time":28.206,
    "FP1_AvgSector2Time":34.07296,
    "FP1_BestSector3Time":28.651,
    "FP1_AvgSector3Time":33.78724,
    "FP1_Laps_SOFT":9.0,
    "FP1_Laps_MEDIUM":16.0,
    "FP1_Laps_HARD":0.0,
    "FP1_Laps_INTERMEDIATE":0.0,
    "FP1_Laps_WET":0.0,
    "FP1_MaxTyreAge":16.0,
    "FP1_AvgTyreAge":7.24,
    "FP1_MaxTrapSpeed":326.0,
    "FP1_AvgSpeed":248.2375189489,
    "FP1_AvgThrottle":80.2486547161,
    "FP1_FullThrottlePct":0.5230312036,
    "FP1_BrakingPct":0.1054977712,
    "FP1_DRSDeploymentPct":0.2674591382,
    "FP2_AvgLapTime":108.3543571429,
    "FP2_BestLapTime":88.267,
    "FP2_LapTimeStd":21.3793616894,
    "FP2_LapCount":14.0,
    "FP2_BestSector1Time":32.063,
    "FP2_AvgSector1Time":42.59025,
    "FP2_BestSector2Time":27.898,
    "FP2_AvgSector2Time":35.3708,
    "FP2_BestSector3Time":28.195,
    "FP2_AvgSector3Time":36.08305,
    "FP2_Laps_SOFT":6.0,
    "FP2_Laps_MEDIUM":15.0,
    "FP2_Laps_HARD":0.0,
    "FP2_Laps_INTERMEDIATE":0.0,
    "FP2_Laps_WET":0.0,
    "FP2_MaxTyreAge":15.0,
    "FP2_AvgTyreAge":6.7142857143,
    "FP2_MaxTrapSpeed":328.0,
    "FP2_AvgSpeed":247.4009986564,
    "FP2_AvgThrottle":77.8279030302,
    "FP2_FullThrottlePct":0.4680851064,
    "FP2_BrakingPct":0.1246200608,
    "FP2_DRSDeploymentPct":0.2416413374,
    "FP3_AvgLapTime":111.4234545455,
    "FP3_BestLapTime":87.489,
    "FP3_LapTimeStd":24.7417575825,
    "FP3_LapCount":11.0,
    "FP3_BestSector1Time":31.769,
    "FP3_AvgSector1Time":46.4068571429,
    "FP3_BestSector2Time":27.67,
    "FP3_AvgSector2Time":37.5623333333,
    "FP3_BestSector3Time":27.954,
    "FP3_AvgSector3Time":37.5348333333,
    "FP3_Laps_SOFT":18.0,
    "FP3_Laps_MEDIUM":0.0,
    "FP3_Laps_HARD":0.0,
    "FP3_Laps_INTERMEDIATE":0.0,
    "FP3_Laps_WET":0.0,
    "FP3_MaxTyreAge":9.0,
    "FP3_AvgTyreAge":5.0,
    "FP3_MaxTrapSpeed":334.0,
    "FP3_AvgSpeed":253.1472376208,
    "FP3_AvgThrottle":79.4985818756,
    "FP3_FullThrottlePct":0.496328928,
    "FP3_BrakingPct":0.1027900147,
    "FP3_DRSDeploymentPct":0.2599118943,
    "MaxTrapSpeed":334.0,
    "AvgTrapSpeed":329.3333333333,
    "FullThrottlePct":0.4958150793,
    "BrakingPct":0.1109692822,
    "DRSDeploymentPct":0.2563374566,
    "BrakePointDelta":16.0811547271,
    "AvgAirTemp":29.0129783951,
    "AvgTrackTemp":44.2638528807,
    "AvgHumidity":58.9753600823,
    "AvgWindSpeed":1.4758899177,
    "AvgWindDirection":235.7989711934,
    "TrackTempDeltaFP1toFP3":1.7491820988
  },
  {
    "Driver":"OCO",
    "FP1_AvgLapTime":109.4757142857,
    "FP1_BestLapTime":91.029,
    "FP1_LapTimeStd":21.9538297077,
    "FP1_LapCount":14.0,
    "FP1_BestSector1Time":33.261,
    "FP1_AvgSector1Time":44.3884705882,
    "FP1_BestSector2Time":28.718,
    "FP1_AvgSector2Time":36.0136666667,
    "FP1_BestSector3Time":29.05,
    "FP1_AvgSector3Time":37.5234285714,
    "FP1_Laps_SOFT":7.0,
    "FP1_Laps_MEDIUM":0.0,
    "FP1_Laps_HARD":14.0,
    "FP1_Laps_INTERMEDIATE":0.0,
    "FP1_Laps_WET":0.0,
    "FP1_MaxTyreAge":14.0,
    "FP1_AvgTyreAge":6.3333333333,
    "FP1_MaxTrapSpeed":325.0,
    "FP1_AvgSpeed":242.4694146282,
    "FP1_AvgThrottle":80.068254682,
    "FP1_FullThrottlePct":0.6908284024,
    "FP1_BrakingPct":0.150887574,
    "FP1_DRSDeploymentPct":0.2485207101,
    "FP2_AvgLapTime":105.40475,
    "FP2_BestLapTime":90.019,
    "FP2_LapTimeStd":19.2366282205,
    "FP2_LapCount":12.0,
    "FP2_BestSector1Time":32.91,
    "FP2_AvgSector1Time":45.2950555556,
    "FP2_BestSector2Time":28.354,
    "FP2_AvgSector2Time":37.4347619048,
    "FP2_BestSector3Time":28.569,
    "FP2_AvgSector3Time":37.5241904762,
    "FP2_Laps_SOFT":11.0,
    "FP2_Laps_MEDIUM":11.0,
    "FP2_Laps_HARD":0.0,
    "FP2_Laps_INTERMEDIATE":0.0,
    "FP2_Laps_WET":0.0,
    "FP2_MaxTyreAge":11.0,
    "FP2_AvgTyreAge":6.0,
    "FP2_MaxTrapSpeed":335.0,
    "FP2_AvgSpeed":245.4896276073,
    "FP2_AvgThrottle":79.7769636621,
    "FP2_FullThrottlePct":0.656626506,
    "FP2_BrakingPct":0.1656626506,
    "FP2_DRSDeploymentPct":0.2515060241,
    "FP3_AvgLapTime":107.8216,
    "FP3_BestLapTime":89.336,
    "FP3_LapTimeStd":20.638739423,
    "FP3_LapCount":15.0,
    "FP3_BestSector1Time":32.597,
    "FP3_AvgSector1Time":40.1128,
    "FP3_BestSector2Time":28.207,
    "FP3_AvgSector2Time":34.61835,
    "FP3_BestSector3Time":28.532,
    "FP3_AvgSector3Time":34.83245,
    "FP3_Laps_SOFT":20.0,
    "FP3_Laps_MEDIUM":0.0,
    "FP3_Laps_HARD":0.0,
    "FP3_Laps_INTERMEDIATE":0.0,
    "FP3_Laps_WET":0.0,
    "FP3_MaxTyreAge":14.0,
    "FP3_AvgTyreAge":6.3,
    "FP3_MaxTrapSpeed":338.0,
    "FP3_AvgSpeed":247.0973697512,
    "FP3_AvgThrottle":79.4305723766,
    "FP3_FullThrottlePct":0.6700581395,
    "FP3_BrakingPct":0.148255814,
    "FP3_DRSDeploymentPct":0.25,
    "MaxTrapSpeed":338.0,
    "AvgTrapSpeed":332.6666666667,
    "FullThrottlePct":0.6725043493,
    "BrakingPct":0.1549353462,
    "DRSDeploymentPct":0.2500089114,
    "BrakePointDelta":10.3980065789,
    "AvgAirTemp":29.0129783951,
    "AvgTrackTemp":44.2638528807,
    "AvgHumidity":58.9753600823,
    "AvgWindSpeed":1.4758899177,
    "AvgWindDirection":235.7989711934,
    "TrackTempDeltaFP1toFP3":1.7491820988
  },
  {
    "Driver":"PIA",
    "FP1_AvgLapTime":105.9807368421,
    "FP1_BestLapTime":89.341,
    "FP1_LapTimeStd":20.2682514398,
    "FP1_LapCount":19.0,
    "FP1_BestSector1Time":32.392,
    "FP1_AvgSector1Time":40.8435,
    "FP1_BestSector2Time":28.242,
    "FP1_AvgSector2Time":35.02848,
    "FP1_BestSector3Time":28.619,
    "FP1_AvgSector3Time":36.27932,
    "FP1_Laps_SOFT":11.0,
    "FP1_Laps_MEDIUM":14.0,
    "FP1_Laps_HARD":0.0,
    "FP1_Laps_INTERMEDIATE":0.0,
    "FP1_Laps_WET":0.0,
    "FP1_MaxTyreAge":14.0,
    "FP1_AvgTyreAge":6.84,
    "FP1_MaxTrapSpeed":329.0,
    "FP1_AvgSpeed":244.6670354181,
    "FP1_AvgThrottle":79.0186381685,
    "FP1_FullThrottlePct":0.637829912,
    "FP1_BrakingPct":0.1290322581,
    "FP1_DRSDeploymentPct":0.2463343109,
    "FP2_AvgLapTime":110.3618125,
    "FP2_BestLapTime":88.43,
    "FP2_LapTimeStd":22.0187836455,
    "FP2_LapCount":16.0,
    "FP2_BestSector1Time":32.215,
    "FP2_AvgSector1Time":42.7303888889,
    "FP2_BestSector2Time":28.025,
    "FP2_AvgSector2Time":33.899952381,
    "FP2_BestSector3Time":28.19,
    "FP2_AvgSector3Time":35.5646190476,
    "FP2_Laps_SOFT":8.0,
    "FP2_Laps_MEDIUM":14.0,
    "FP2_Laps_HARD":0.0,
    "FP2_Laps_INTERMEDIATE":0.0,
    "FP2_Laps_WET":0.0,
    "FP2_MaxTyreAge":14.0,
    "FP2_AvgTyreAge":6.4090909091,
    "FP2_MaxTrapSpeed":327.0,
    "FP2_AvgSpeed":248.808281471,
    "FP2_AvgThrottle":79.1999635535,
    "FP2_FullThrottlePct":0.6125730994,
    "FP2_BrakingPct":0.115497076,
    "FP2_DRSDeploymentPct":0.25,
    "FP3_AvgLapTime":116.243,
    "FP3_BestLapTime":87.513,
    "FP3_LapTimeStd":22.896942444,
    "FP3_LapCount":15.0,
    "FP3_BestSector1Time":31.827,
    "FP3_AvgSector1Time":45.1327333333,
    "FP3_BestSector2Time":27.587,
    "FP3_AvgSector2Time":34.6045263158,
    "FP3_BestSector3Time":28.076,
    "FP3_AvgSector3Time":37.2840526316,
    "FP3_Laps_SOFT":19.0,
    "FP3_Laps_MEDIUM":0.0,
    "FP3_Laps_HARD":0.0,
    "FP3_Laps_INTERMEDIATE":0.0,
    "FP3_Laps_WET":0.0,
    "FP3_MaxTyreAge":10.0,
    "FP3_AvgTyreAge":5.2631578947,
    "FP3_MaxTrapSpeed":332.0,
    "FP3_AvgSpeed":251.7872514348,
    "FP3_AvgThrottle":80.4660812906,
    "FP3_FullThrottlePct":0.5919282511,
    "FP3_BrakingPct":0.1016442451,
    "FP3_DRSDeploymentPct":0.2421524664,
    "MaxTrapSpeed":332.0,
    "AvgTrapSpeed":329.3333333333,
    "FullThrottlePct":0.6141104209,
    "BrakingPct":0.1153911931,
    "DRSDeploymentPct":0.2461622591,
    "BrakePointDelta":5.1524510234,
    "AvgAirTemp":29.0129783951,
    "AvgTrackTemp":44.2638528807,
    "AvgHumidity":58.9753600823,
    "AvgWindSpeed":1.4758899177,
    "AvgWindDirection":235.7989711934,
    "TrackTempDeltaFP1toFP3":1.7491820988
  },
  {
    "Driver":"RUS",
    "FP1_AvgLapTime":104.8619230769,
    "FP1_BestLapTime":89.618,
    "FP1_LapTimeStd":19.7898211271,
    "FP1_LapCount":13.0,
    "FP1_BestSector1Time":32.626,
    "FP1_AvgSector1Time":47.5198888889,
    "FP1_BestSector2Time":28.2,
    "FP1_AvgSector2Time":37.1510952381,
    "FP1_BestSector3Time":28.736,
    "FP1_AvgSector3Time":37.0801428571,
    "FP1_Laps_SOFT":5.0,
    "FP1_Laps_MEDIUM":16.0,
    "FP1_Laps_HARD":0.0,
    "FP1_Laps_INTERMEDIATE":0.0,
    "FP1_Laps_WET":0.0,
    "FP1_MaxTyreAge":16.0,
    "FP1_AvgTyreAge":7.1904761905,
    "FP1_MaxTrapSpeed":328.0,
    "FP1_AvgSpeed":246.3642542133,
    "FP1_AvgThrottle":80.4321359785,
    "FP1_FullThrottlePct":0.7212389381,
    "FP1_BrakingPct":0.1297935103,
    "FP1_DRSDeploymentPct":0.2477876106,
    "FP2_AvgLapTime":112.3366363636,
    "FP2_BestLapTime":88.973,
    "FP2_LapTimeStd":20.578822266,
    "FP2_LapCount":11.0,
    "FP2_BestSector1Time":32.444,
    "FP2_AvgSector1Time":45.6856470588,
    "FP2_BestSector2Time":28.063,
    "FP2_AvgSector2Time":39.839,
    "FP2_BestSector3Time":28.466,
    "FP2_AvgSector3Time":39.43565,
    "FP2_Laps_SOFT":8.0,
    "FP2_Laps_MEDIUM":13.0,
    "FP2_Laps_HARD":0.0,
    "FP2_Laps_INTERMEDIATE":0.0,
    "FP2_Laps_WET":0.0,
    "FP2_MaxTyreAge":13.0,
    "FP2_AvgTyreAge":6.0476190476,
    "FP2_MaxTrapSpeed":329.0,
    "FP2_AvgSpeed":248.1918857091,
    "FP2_AvgThrottle":81.6780056825,
    "FP2_FullThrottlePct":0.7201767305,
    "FP2_BrakingPct":0.1281296024,
    "FP2_DRSDeploymentPct":0.2621502209,
    "FP3_AvgLapTime":107.3351111111,
    "FP3_BestLapTime":88.116,
    "FP3_LapTimeStd":22.7777947871,
    "FP3_LapCount":9.0,
    "FP3_BestSector1Time":32.046,
    "FP3_AvgSector1Time":50.6966923077,
    "FP3_BestSector2Time":27.733,
    "FP3_AvgSector2Time":37.1732941176,
    "FP3_BestSector3Time":28.319,
    "FP3_AvgSector3Time":36.9201176471,
    "FP3_Laps_SOFT":17.0,
    "FP3_Laps_MEDIUM":0.0,
    "FP3_Laps_HARD":0.0,
    "FP3_Laps_INTERMEDIATE":0.0,
    "FP3_Laps_WET":0.0,
    "FP3_MaxTyreAge":9.0,
    "FP3_AvgTyreAge":4.7647058824,
    "FP3_MaxTrapSpeed":333.0,
    "FP3_AvgSpeed":248.4694304302,
    "FP3_AvgThrottle":81.8809757602,
    "FP3_FullThrottlePct":0.7151515152,
    "FP3_BrakingPct":0.1181818182,
    "FP3_DRSDeploymentPct":0.246969697,
    "MaxTrapSpeed":333.0,
    "AvgTrapSpeed":330.0,
    "FullThrottlePct":0.7188557279,
    "BrakingPct":0.1253683103,
    "DRSDeploymentPct":0.2523025095,
    "BrakePointDelta":-3.6938452729,
    "AvgAirTemp":29.0129783951,
    "AvgTrackTemp":44.2638528807,
    "AvgHumidity":58.9753600823,
    "AvgWindSpeed":1.4758899177,
    "AvgWindDirection":235.7989711934,
    "TrackTempDeltaFP1toFP3":1.7491820988
  },
  {
    "Driver":"SAI",
    "FP1_AvgLapTime":103.1881176471,
    "FP1_BestLapTime":89.779,
    "FP1_LapTimeStd":18.7800516502,
    "FP1_LapCount":17.0,
    "FP1_BestSector1Time":32.604,
    "FP1_AvgSector1Time":43.8143181818,
    "FP1_BestSector2Time":28.323,
    "FP1_AvgSector2Time":36.5009615385,
    "FP1_BestSector3Time":28.738,
    "FP1_AvgSector3Time":35.4941923077,
    "FP1_Laps_SOFT":9.0,
    "FP1_Laps_MEDIUM":0.0,
    "FP1_Laps_HARD":17.0,
    "FP1_Laps_INTERMEDIATE":0.0,
    "FP1_Laps_WET":0.0,
    "FP1_MaxTyreAge":17.0,
    "FP1_AvgTyreAge":7.6153846154,
    "FP1_MaxTrapSpeed":328.0,
    "FP1_AvgSpeed":245.9542142695,
    "FP1_AvgThrottle":78.9607800413,
    "FP1_FullThrottlePct":0.6807228916,
    "FP1_BrakingPct":0.1581325301,
    "FP1_DRSDeploymentPct":0.2530120482,
    "FP2_AvgLapTime":107.133875,
    "FP2_BestLapTime":88.942,
    "FP2_LapTimeStd":21.9783967989,
    "FP2_LapCount":16.0,
    "FP2_BestSector1Time":32.43,
    "FP2_AvgSector1Time":44.0899,
    "FP2_BestSector2Time":28.113,
    "FP2_AvgSector2Time":36.5715652174,
    "FP2_BestSector3Time":28.399,
    "FP2_AvgSector3Time":34.7696086957,
    "FP2_Laps_SOFT":6.0,
    "FP2_Laps_MEDIUM":18.0,
    "FP2_Laps_HARD":0.0,
    "FP2_Laps_INTERMEDIATE":0.0,
    "FP2_Laps_WET":0.0,
    "FP2_MaxTyreAge":18.0,
    "FP2_AvgTyreAge":8.0,
    "FP2_MaxTrapSpeed":332.0,
    "FP2_AvgSpeed":246.2985762932,
    "FP2_AvgThrottle":79.8346257419,
    "FP2_FullThrottlePct":0.6939078752,
    "FP2_BrakingPct":0.1396731055,
    "FP2_DRSDeploymentPct":0.2481426449,
    "FP3_AvgLapTime":116.5614,
    "FP3_BestLapTime":88.57,
    "FP3_LapTimeStd":21.0846151821,
    "FP3_LapCount":10.0,
    "FP3_BestSector1Time":32.239,
    "FP3_AvgSector1Time":44.3297272727,
    "FP3_BestSector2Time":27.954,
    "FP3_AvgSector2Time":38.5438,
    "FP3_BestSector3Time":28.377,
    "FP3_AvgSector3Time":36.8416,
    "FP3_Laps_SOFT":15.0,
    "FP3_Laps_MEDIUM":0.0,
    "FP3_Laps_HARD":0.0,
    "FP3_Laps_INTERMEDIATE":0.0,
    "FP3_Laps_WET":0.0,
    "FP3_MaxTyreAge":9.0,
    "FP3_AvgTyreAge":4.4,
    "FP3_MaxTrapSpeed":333.0,
    "FP3_AvgSpeed":247.5331474293,
    "FP3_AvgThrottle":81.2895351632,
    "FP3_FullThrottlePct":0.7078488372,
    "FP3_BrakingPct":0.1308139535,
    "FP3_DRSDeploymentPct":0.2456395349,
    "MaxTrapSpeed":333.0,
    "AvgTrapSpeed":331.0,
    "FullThrottlePct":0.694159868,
    "BrakingPct":0.1428731964,
    "DRSDeploymentPct":0.2489314093,
    "BrakePointDelta":10.6427288012,
    "AvgAirTemp":29.0129783951,
    "AvgTrackTemp":44.2638528807,
    "AvgHumidity":58.9753600823,
    "AvgWindSpeed":1.4758899177,
    "AvgWindDirection":235.7989711934,
    "TrackTempDeltaFP1toFP3":1.7491820988
  },
  {
    "Driver":"STR",
    "FP1_AvgLapTime":103.9788571429,
    "FP1_BestLapTime":90.583,
    "FP1_LapTimeStd":20.093712334,
    "FP1_LapCount":14.0,
    "FP1_BestSector1Time":32.921,
    "FP1_AvgSector1Time":45.3099,
    "FP1_BestSector2Time":28.657,
    "FP1_AvgSector2Time":37.5469565217,
    "FP1_BestSector3Time":28.863,
    "FP1_AvgSector3Time":38.0260434783,
    "FP1_Laps_SOFT":14.0,
    "FP1_Laps_MEDIUM":9.0,
    "FP1_Laps_HARD":0.0,
    "FP1_Laps_INTERMEDIATE":0.0,
    "FP1_Laps_WET":0.0,
    "FP1_MaxTyreAge":14.0,
    "FP1_AvgTyreAge":6.5217391304,
    "FP1_MaxTrapSpeed":327.0,
    "FP1_AvgSpeed":244.2441731933,
    "FP1_AvgThrottle":81.069805439,
    "FP1_FullThrottlePct":0.7466666667,
    "FP1_BrakingPct":0.1155555556,
    "FP1_DRSDeploymentPct":0.2592592593,
    "FP2_AvgLapTime":111.936625,
    "FP2_BestLapTime":90.007,
    "FP2_LapTimeStd":25.9042306635,
    "FP2_LapCount":8.0,
    "FP2_BestSector1Time":32.79,
    "FP2_AvgSector1Time":54.2445714286,
    "FP2_BestSector2Time":28.468,
    "FP2_AvgSector2Time":38.4495294118,
    "FP2_BestSector3Time":28.749,
    "FP2_AvgSector3Time":39.5714117647,
    "FP2_Laps_SOFT":14.0,
    "FP2_Laps_MEDIUM":4.0,
    "FP2_Laps_HARD":0.0,
    "FP2_Laps_INTERMEDIATE":0.0,
    "FP2_Laps_WET":0.0,
    "FP2_MaxTyreAge":14.0,
    "FP2_AvgTyreAge":6.3888888889,
    "FP2_MaxTrapSpeed":326.0,
    "FP2_AvgSpeed":242.2900966265,
    "FP2_AvgThrottle":79.6701475252,
    "FP2_FullThrottlePct":0.7016248154,
    "FP2_BrakingPct":0.1211225997,
    "FP2_DRSDeploymentPct":0.246676514,
    "FP3_AvgLapTime":108.6155,
    "FP3_BestLapTime":89.478,
    "FP3_LapTimeStd":23.4652606219,
    "FP3_LapCount":10.0,
    "FP3_BestSector1Time":32.419,
    "FP3_AvgSector1Time":52.3426666667,
    "FP3_BestSector2Time":28.153,
    "FP3_AvgSector2Time":37.677,
    "FP3_BestSector3Time":28.762,
    "FP3_AvgSector3Time":38.3191578947,
    "FP3_Laps_SOFT":16.0,
    "FP3_Laps_MEDIUM":1.0,
    "FP3_Laps_HARD":2.0,
    "FP3_Laps_INTERMEDIATE":0.0,
    "FP3_Laps_WET":0.0,
    "FP3_MaxTyreAge":10.0,
    "FP3_AvgTyreAge":4.1578947368,
    "FP3_MaxTrapSpeed":329.0,
    "FP3_AvgSpeed":244.4756563898,
    "FP3_AvgThrottle":80.0565620325,
    "FP3_FullThrottlePct":0.7392550143,
    "FP3_BrakingPct":0.1260744986,
    "FP3_DRSDeploymentPct":0.2435530086,
    "MaxTrapSpeed":329.0,
    "AvgTrapSpeed":327.3333333333,
    "FullThrottlePct":0.7291821655,
    "BrakingPct":0.1209175513,
    "DRSDeploymentPct":0.249829594,
    "BrakePointDelta":1.0851362086,
    "AvgAirTemp":29.0129783951,
    "AvgTrackTemp":44.2638528807,
    "AvgHumidity":58.9753600823,
    "AvgWindSpeed":1.4758899177,
    "AvgWindDirection":235.7989711934,
    "TrackTempDeltaFP1toFP3":1.7491820988
  },
  {
    "Driver":"TSU",
    "FP1_AvgLapTime":101.071375,
    "FP1_BestLapTime":89.821,
    "FP1_LapTimeStd":14.9250126337,
    "FP1_LapCount":16.0,
    "FP1_BestSector1Time":32.543,
    "FP1_AvgSector1Time":47.5235217391,
    "FP1_BestSector2Time":28.349,
    "FP1_AvgSector2Time":35.7157692308,
    "FP1_BestSector3Time":28.817,
    "FP1_AvgSector3Time":36.01,
    "FP1_Laps_SOFT":6.0,
    "FP1_Laps_MEDIUM":20.0,
    "FP1_Laps_HARD":0.0,
    "FP1_Laps_INTERMEDIATE":0.0,
    "FP1_Laps_WET":0.0,
    "FP1_MaxTyreAge":20.0,
    "FP1_AvgTyreAge":8.8846153846,
    "FP1_MaxTrapSpeed":328.0,
    "FP1_AvgSpeed":245.3328238371,
    "FP1_AvgThrottle":81.7758551738,
    "FP1_FullThrottlePct":0.7170658683,
    "FP1_BrakingPct":0.1002994012,
    "FP1_DRSDeploymentPct":0.254491018,
    "FP2_AvgLapTime":108.013,
    "FP2_BestLapTime":88.963,
    "FP2_LapTimeStd":23.1847660286,
    "FP2_LapCount":11.0,
    "FP2_BestSector1Time":32.239,
    "FP2_AvgSector1Time":48.003125,
    "FP2_BestSector2Time":28.237,
    "FP2_AvgSector2Time":37.1274210526,
    "FP2_BestSector3Time":28.487,
    "FP2_AvgSector3Time":36.3872777778,
    "FP2_Laps_SOFT":6.0,
    "FP2_Laps_MEDIUM":13.0,
    "FP2_Laps_HARD":0.0,
    "FP2_Laps_INTERMEDIATE":0.0,
    "FP2_Laps_WET":0.0,
    "FP2_MaxTyreAge":13.0,
    "FP2_AvgTyreAge":5.8947368421,
    "FP2_MaxTrapSpeed":332.0,
    "FP2_AvgSpeed":247.6911738663,
    "FP2_AvgThrottle":81.3151672804,
    "FP2_FullThrottlePct":0.7050147493,
    "FP2_BrakingPct":0.1150442478,
    "FP2_DRSDeploymentPct":0.2551622419,
    "FP3_AvgLapTime":118.8516,
    "FP3_BestLapTime":88.67,
    "FP3_LapTimeStd":27.5907106316,
    "FP3_LapCount":10.0,
    "FP3_BestSector1Time":32.22,
    "FP3_AvgSector1Time":47.7127272727,
    "FP3_BestSector2Time":27.935,
    "FP3_AvgSector2Time":38.2714285714,
    "FP3_BestSector3Time":28.509,
    "FP3_AvgSector3Time":36.9098571429,
    "FP3_Laps_SOFT":14.0,
    "FP3_Laps_MEDIUM":0.0,
    "FP3_Laps_HARD":0.0,
    "FP3_Laps_INTERMEDIATE":0.0,
    "FP3_Laps_WET":0.0,
    "FP3_MaxTyreAge":8.0,
    "FP3_AvgTyreAge":4.0714285714,
    "FP3_MaxTrapSpeed":334.0,
    "FP3_AvgSpeed":247.6176482092,
    "FP3_AvgThrottle":80.4280470453,
    "FP3_FullThrottlePct":0.6955882353,
    "FP3_BrakingPct":0.1147058824,
    "FP3_DRSDeploymentPct":0.25,
    "MaxTrapSpeed":334.0,
    "AvgTrapSpeed":331.3333333333,
    "FullThrottlePct":0.7058896176,
    "BrakingPct":0.1100165104,
    "DRSDeploymentPct":0.2532177533,
    "BrakePointDelta":12.0879139864,
    "AvgAirTemp":29.0129783951,
    "AvgTrackTemp":44.2638528807,
    "AvgHumidity":58.9753600823,
    "AvgWindSpeed":1.4758899177,
    "AvgWindDirection":235.7989711934,
    "TrackTempDeltaFP1toFP3":1.7491820988
  },
  {
    "Driver":"VER",
    "FP1_AvgLapTime":103.6246842105,
    "FP1_BestLapTime":89.818,
    "FP1_LapTimeStd":16.7873585046,
    "FP1_LapCount":19.0,
    "FP1_BestSector1Time":32.69,
    "FP1_AvgSector1Time":43.3355652174,
    "FP1_BestSector2Time":28.382,
    "FP1_AvgSector2Time":34.8974230769,
    "FP1_BestSector3Time":28.746,
    "FP1_AvgSector3Time":35.1022692308,
    "FP1_Laps_SOFT":5.0,
    "FP1_Laps_MEDIUM":21.0,
    "FP1_Laps_HARD":0.0,
    "FP1_Laps_INTERMEDIATE":0.0,
    "FP1_Laps_WET":0.0,
    "FP1_MaxTyreAge":21.0,
    "FP1_AvgTyreAge":9.4615384615,
    "FP1_MaxTrapSpeed":330.0,
    "FP1_AvgSpeed":244.3534716862,
    "FP1_AvgThrottle":82.5727032603,
    "FP1_FullThrottlePct":0.7440828402,
    "FP1_BrakingPct":0.1272189349,
    "FP1_DRSDeploymentPct":0.2485207101,
    "FP2_AvgLapTime":104.906,
    "FP2_BestLapTime":88.547,
    "FP2_LapTimeStd":19.0775697719,
    "FP2_LapCount":16.0,
    "FP2_BestSector1Time":32.161,
    "FP2_AvgSector1Time":40.8019473684,
    "FP2_BestSector2Time":28.029,
    "FP2_AvgSector2Time":34.6795,
    "FP2_BestSector3Time":28.357,
    "FP2_AvgSector3Time":34.2416818182,
    "FP2_Laps_SOFT":6.0,
    "FP2_Laps_MEDIUM":17.0,
    "FP2_Laps_HARD":0.0,
    "FP2_Laps_INTERMEDIATE":0.0,
    "FP2_Laps_WET":0.0,
    "FP2_MaxTyreAge":17.0,
    "FP2_AvgTyreAge":7.5652173913,
    "FP2_MaxTrapSpeed":332.0,
    "FP2_AvgSpeed":248.3904165112,
    "FP2_AvgThrottle":82.0708727513,
    "FP2_FullThrottlePct":0.7389984825,
    "FP2_BrakingPct":0.1138088012,
    "FP2_DRSDeploymentPct":0.2655538695,
    "FP3_AvgLapTime":113.3058888889,
    "FP3_BestLapTime":88.334,
    "FP3_LapTimeStd":25.6032023654,
    "FP3_LapCount":9.0,
    "FP3_BestSector1Time":32.077,
    "FP3_AvgSector1Time":44.1753,
    "FP3_BestSector2Time":27.875,
    "FP3_AvgSector2Time":35.2942142857,
    "FP3_BestSector3Time":28.312,
    "FP3_AvgSector3Time":37.6251428571,
    "FP3_Laps_SOFT":14.0,
    "FP3_Laps_MEDIUM":0.0,
    "FP3_Laps_HARD":0.0,
    "FP3_Laps_INTERMEDIATE":0.0,
    "FP3_Laps_WET":0.0,
    "FP3_MaxTyreAge":8.0,
    "FP3_AvgTyreAge":4.0714285714,
    "FP3_MaxTrapSpeed":338.0,
    "FP3_AvgSpeed":249.3808069961,
    "FP3_AvgThrottle":81.1342686728,
    "FP3_FullThrottlePct":0.7362962963,
    "FP3_BrakingPct":0.1274074074,
    "FP3_DRSDeploymentPct":0.2533333333,
    "MaxTrapSpeed":338.0,
    "AvgTrapSpeed":333.3333333333,
    "FullThrottlePct":0.7397925397,
    "BrakingPct":0.1228117145,
    "DRSDeploymentPct":0.2558026376,
    "BrakePointDelta":0.7409695419,
    "AvgAirTemp":29.0129783951,
    "AvgTrackTemp":44.2638528807,
    "AvgHumidity":58.9753600823,
    "AvgWindSpeed":1.4758899177,
    "AvgWindDirection":235.7989711934,
    "TrackTempDeltaFP1toFP3":1.7491820988
  }
]